blurr/__init__.py
blurr/_nbdev.py
blurr/callbacks.py
blurr/index.py
blurr/utils.py
blurr/text/__init__.py
blurr/text/callbacks.py
blurr/text/utils.py
blurr/text/data/__init__.py
blurr/text/data/all.py
blurr/text/data/core.py
blurr/text/data/language_modeling.py
blurr/text/data/question_answering.py
blurr/text/data/token_classification.py
blurr/text/data/seq2seq/__init__.py
blurr/text/data/seq2seq/core.py
blurr/text/data/seq2seq/summarization.py
blurr/text/data/seq2seq/translation.py
blurr/text/modeling/__init__.py
blurr/text/modeling/all.py
blurr/text/modeling/core.py
blurr/text/modeling/language_modeling.py
blurr/text/modeling/question_answering.py
blurr/text/modeling/token_classification.py
blurr/text/modeling/seq2seq/__init__.py
blurr/text/modeling/seq2seq/core.py
blurr/text/modeling/seq2seq/summarization.py
blurr/text/modeling/seq2seq/translation.py
ohmeow_blurr-1.0.5.dist-info/LICENSE
ohmeow_blurr-1.0.5.dist-info/METADATA
ohmeow_blurr-1.0.5.dist-info/WHEEL
ohmeow_blurr-1.0.5.dist-info/entry_points.txt
ohmeow_blurr-1.0.5.dist-info/top_level.txt
ohmeow_blurr-1.0.5.dist-info/RECORD
