Metadata-Version: 2.1
Name: ohmeow-blurr
Version: 1.0.5
Summary: A library designed for fastai developers who want to train and deploy Hugging Face transformers
Home-page: https://github.com/ohmeow/blurr/tree/master/
Author: Wayde Gilliam
Author-email: wgilliam@ohmeow.com
License: Apache Software License 2.0
Keywords: fastai huggingface transformers classification ner "token classification" "question answer" summarization translation "language modeling"
Platform: UNKNOWN
Classifier: Development Status :: 2 - Pre-Alpha
Classifier: Intended Audience :: Developers
Classifier: License :: OSI Approved :: Apache Software License
Classifier: Natural Language :: English
Classifier: Programming Language :: Python :: 3.7
Classifier: Programming Language :: Python :: 3.8
Classifier: Programming Language :: Python :: 3.9
Requires-Python: >=3.7
License-File: LICENSE
Requires-Dist: torch (<2.0.0,>=1.7.0)
Requires-Dist: fastcore (>=1.4.1)
Requires-Dist: fastai (>=2.5)
Requires-Dist: transformers (>=4.6)
Requires-Dist: datasets
Requires-Dist: sentencepiece
Requires-Dist: seqeval
Requires-Dist: rouge-score
Requires-Dist: openpyxl (<4.0,>=3.0.7)
Requires-Dist: xlrd (<3.0,>=2.0.1)
Provides-Extra: dev
Requires-Dist: ipykernel ; extra == 'dev'
Requires-Dist: nbdev ; extra == 'dev'
Requires-Dist: gputil ; extra == 'dev'
